eth_alarm_client/__init__.py
eth_alarm_client/block_sage.py
eth_alarm_client/call_contract.py
eth_alarm_client/cli.py
eth_alarm_client/contracts.json
eth_alarm_client/contracts.py
eth_alarm_client/scheduler.py
eth_alarm_client/utils.py
ethereum_alarm_clock_client-7.0.0.dist-info/DESCRIPTION.rst
ethereum_alarm_clock_client-7.0.0.dist-info/METADATA
ethereum_alarm_clock_client-7.0.0.dist-info/RECORD
ethereum_alarm_clock_client-7.0.0.dist-info/WHEEL
ethereum_alarm_clock_client-7.0.0.dist-info/entry_points.txt
ethereum_alarm_clock_client-7.0.0.dist-info/metadata.json
ethereum_alarm_clock_client-7.0.0.dist-info/top_level.txt
