Metadata-Version: 2.0
Name: ethereum-alarm-clock-client
Version: 7.0.0
Summary: Ethereum Alarm Clock Client
Home-page: http://www.ethereum-alarm-clock.com
Author: Piper Merriam
Author-email: pipermerriam@gmail.com
License: MIT
Keywords: ethereum
Platform: UNKNOWN
Classifier: Development Status :: 2 - Pre-Alpha
Classifier: Intended Audience :: Developers
Classifier: License :: OSI Approved :: BSD License
Classifier: Natural Language :: English
Classifier: Programming Language :: Python :: 2
Classifier: Programming Language :: Python :: 2.7
Classifier: Programming Language :: Python :: 3
Classifier: Programming Language :: Python :: 3.3
Classifier: Programming Language :: Python :: 3.4
Requires-Dist: ethereum-ipc-client (>=0.1.9)
Requires-Dist: ethereum-rpc-client (>=0.4.4)
Requires-Dist: populus (>=0.7.2)
